newnow/__init__.py
newnow/utils/__init__.py
newnow/utils/visualization/__init__.py
newnow/utils/visualization/line_plot.py
newnowlib-0.1.0.dist-info/METADATA
newnowlib-0.1.0.dist-info/WHEEL
newnowlib-0.1.0.dist-info/top_level.txt
newnowlib-0.1.0.dist-info/RECORD
